machinepy/__init__.py
machinepy/Classification/__init__.py
machinepy/Classification/KNN/__init__.py
machinepy/Classification/KNN/knn.py
machinepy/Classification/LDA/__init__.py
machinepy/Classification/LDA/lda.py
machinepy/Classification/Logistic Regression/__init__.py
machinepy/Classification/Logistic Regression/logistic_reg.py
machinepy/Classification/Logistic Regression L1/Logistic_lasso_reg.py
machinepy/Classification/Logistic Regression L1/__init__.py
machinepy/Classification/Logistic Regression L1L2/__init__.py
machinepy/Classification/Logistic Regression L1L2/logistic_elasticnet_reg.py
machinepy/Classification/Logitic Regression L2/__init__.py
machinepy/Classification/Logitic Regression L2/logistic_ridge_reg.py
machinepy/Classification/Naive Bayes/__init__.py
machinepy/Classification/Naive Bayes/gaussian_NB.py
machinepy/Classification/Perceptron/__init__.py
machinepy/Classification/Perceptron/perceptron.py
machinepy/Classification/QDA/QDAClassifier.py
machinepy/Classification/QDA/__init__.py
machinepy/Classification/RBF Neural Net/RBFN.py
machinepy/Classification/RBF Neural Net/__init__.py
machinepy/Classification/SVM/__init__.py
machinepy/Classification/SVM/svm.py
machinepy/Clustering/__init__.py
machinepy/Clustering/Fuzzy C-Mean/__init__.py
machinepy/Clustering/Fuzzy C-Mean/cmeans.py
machinepy/Clustering/Gaussian Mixture Model/GMM.py
machinepy/Clustering/Gaussian Mixture Model/__init__.py
machinepy/Clustering/Heirarchical Clustering/HCA.py
machinepy/Clustering/Heirarchical Clustering/__init__.py
machinepy/Clustering/K-Means/K-Means.py
machinepy/Clustering/K-Means/__init__.py
machinepy/Clustering/K-Means++/K-mean_pp.py
machinepy/Clustering/K-Means++/__init__.py
machinepy/Clustering/K-Median/__init__.py
machinepy/Clustering/K-Median/k_median.py
machinepy/Clustering/K-Median++/__init__.py
machinepy/Clustering/K-Median++/kmedian_pp.py
machinepy/Clustering/Mean-Shift/__init__.py
machinepy/Clustering/Mean-Shift/mean_shift.py
machine_py-0.0.1.dist-info/LICENSE
machine_py-0.0.1.dist-info/METADATA
machine_py-0.0.1.dist-info/WHEEL
machine_py-0.0.1.dist-info/top_level.txt
machine_py-0.0.1.dist-info/RECORD
