Metadata-Version: 2.1
Name: machine-py
Version: 0.0.1
Summary: A package for machine learning
Home-page: UNKNOWN
Author: Prashant Lawhatre & Pranay Lawhatre
Author-email: prashantlawhatre@gmail.com
License: UNKNOWN
Platform: UNKNOWN
Requires-Dist: matplotlib
Requires-Dist: numpy
Requires-Dist: sympy
